pymin/__init__.py
pymin/__main__.py
pymin/cli.py
pymin/commands/__init__.py
pymin/commands/package/__init__.py
pymin/commands/package/add_command.py
pymin/commands/package/fix_command.py
pymin/commands/package/list_command.py
pymin/commands/package/remove_command.py
pymin/commands/package/update_command.py
pymin/commands/pypi/__init__.py
pymin/commands/pypi/check_command.py
pymin/commands/pypi/release_command.py
pymin/commands/pypi/search_command.py
pymin/commands/venv/__init__.py
pymin/commands/venv/activate_command.py
pymin/commands/venv/deactivate_command.py
pymin/commands/venv/info_command.py
pymin/commands/venv/venv_command.py
pymin/core/__init__.py
pymin/core/check.py
pymin/core/events.py
pymin/core/exceptions.py
pymin/core/package_analyzer.py
pymin/core/package_manager.py
pymin/core/package_publisher.py
pymin/core/pyproject_manager.py
pymin/core/release.py
pymin/core/search.py
pymin/core/security.py
pymin/core/similarity.py
pymin/core/system_analyzer.py
pymin/core/validators.py
pymin/core/venv_analyzer.py
pymin/core/venv_manager.py
pymin/core/version_checker.py
pymin/core/version_utils.py
pymin/ui/__init__.py
pymin/ui/console.py
pymin/ui/env_view.py
pymin/ui/formatting.py
pymin/ui/style.py
pymin-0.0.21.dist-info/LICENSE
pymin-0.0.21.dist-info/METADATA
pymin-0.0.21.dist-info/WHEEL
pymin-0.0.21.dist-info/entry_points.txt
pymin-0.0.21.dist-info/top_level.txt
pymin-0.0.21.dist-info/RECORD
