Metadata-Version: 2.2
Name: pymin
Version: 0.0.21
Summary: A minimalist Python CLI tool for development workflow. Named after Taiwanese '歹命' (Pháiⁿ-miā), it turns common development pain points into simple solutions, providing package name validation, virtual environment management, and project information display with minimal configuration.
Author-email: Albert Liu <dreamerhyde@gmail.com>
License: MIT
Project-URL: Homepage, https://github.com/TaiwanBigdata/pymin
Project-URL: Repository, https://github.com/TaiwanBigdata/pymin.git
Keywords: pypi,package-validation,package-search,package-check,package-release,cli,virtual-environment,dependency-management,development-tools,package-management,requirements,project-management
Classifier: Development Status :: 4 - Beta
Classifier: Environment :: Console
Classifier: Intended Audience :: Developers
Classifier: License :: OSI Approved :: MIT License
Classifier: Operating System :: OS Independent
Classifier: Programming Language :: Python :: 3
Classifier: Programming Language :: Python :: 3.8
Classifier: Programming Language :: Python :: 3.9
Classifier: Programming Language :: Python :: 3.10
Classifier: Programming Language :: Python :: 3.11
Classifier: Programming Language :: Python :: 3.12
Classifier: Topic :: Software Development
Classifier: Topic :: Software Development :: Build Tools
Classifier: Topic :: Software Development :: Libraries :: Python Modules
Classifier: Topic :: Software Development :: Testing
Classifier: Topic :: System :: Installation/Setup
Classifier: Topic :: System :: Software Distribution
Classifier: Topic :: System :: Systems Administration
Classifier: Topic :: Utilities
Requires-Python: >=3.8
License-File: LICENSE
Requires-Dist: click>=8.0.0
Requires-Dist: packaging>=21.0
Requires-Dist: requests>=2.31.0
Requires-Dist: rich>=10.0.0
Requires-Dist: tomlkit>=0.11.0
Provides-Extra: dev
Requires-Dist: pytest>=7.0.0; extra == "dev"
Requires-Dist: pytest-cov>=4.0.0; extra == "dev"
Requires-Dist: black>=22.0.0; extra == "dev"
Requires-Dist: isort>=5.0.0; extra == "dev"
Requires-Dist: flake8>=4.0.0; extra == "dev"
